pyupdog-1.2.3.data/scripts/UPDog.py
upd/__init__.py
upd/utility_funcs.py
pyupdog-1.2.3.dist-info/METADATA
pyupdog-1.2.3.dist-info/WHEEL
pyupdog-1.2.3.dist-info/top_level.txt
pyupdog-1.2.3.dist-info/RECORD
