Metadata-Version: 2.1
Name: pyupdog
Version: 1.2.3
Summary: Python program for calculating UPD
Home-page: https://github.com/josephhalstead/pyvariantfilter
Author: Joseph Halstead
Author-email: josephhalstead89@gmail.com
Classifier: Programming Language :: Python :: 3
Classifier: Operating System :: OS Independent
Requires-Python: >=3.11
Requires-Dist: pysam (>=0.22.1)
Requires-Dist: pandas (>=2.2)
Requires-Dist: seaborn (>=0.13)
Requires-Dist: scipy (>=1.14)
Requires-Dist: pyvariantfilter (>=2.1.0)
